cdis_oauth2client/__init__.py
cdis_oauth2client/blueprint.py
cdis_oauth2client/client.py
cdis_oauth2client/exceptions.py
cdis_oauth2client/oauth2.py
cdis_oauth2client-2.0.0.dist-info/METADATA
cdis_oauth2client-2.0.0.dist-info/WHEEL
cdis_oauth2client-2.0.0.dist-info/licenses/LICENSE
cdis_oauth2client-2.0.0.dist-info/licenses/NOTICE
cdis_oauth2client-2.0.0.dist-info/RECORD
